flooss/__init__.py
flooss/__main__.py
flooss/aggregation/__init__.py
flooss/aggregation/aggregation.py
flooss/dataframe.py
flooss/google.py
flooss/plot/__init__.py
flooss/plot/plot.py
flooss/report/__init__.py
flooss/report/_display.py
flooss/report/report.py
flooss-0.1.2.dist-info/LICENSE
flooss-0.1.2.dist-info/WHEEL
flooss-0.1.2.dist-info/METADATA
flooss-0.1.2.dist-info/RECORD
