Metadata-Version: 2.1
Name: flooss
Version: 0.1.2
Summary: A Python package to track personal expenses and build meaningful reports.
License: MIT
Author: Taha GHAZOUANI
Author-email: ghazouani.taha@gmail.com
Requires-Python: >=3.7.1,<4.0.0
Classifier: License :: OSI Approved :: MIT License
Classifier: Programming Language :: Python :: 3
Classifier: Programming Language :: Python :: 3.8
Classifier: Programming Language :: Python :: 3.9
Classifier: Programming Language :: Python :: 3.10
Requires-Dist: bokeh (>=2.4.3,<3.0.0)
Requires-Dist: openpyxl (>=3.0.10,<4.0.0)
Requires-Dist: pandas (==1.3.5)
